flex_lumped/FLEX_lumped_bmi.py
flex_lumped/__init__.py
flex_lumped/utils.py
flex_lumped/.ipynb_checkpoints/HBV_bmi-checkpoint.py
flex_lumped-1.0.0.dist-info/METADATA
flex_lumped-1.0.0.dist-info/WHEEL
flex_lumped-1.0.0.dist-info/licenses/LICENSE.txt
flex_lumped-1.0.0.dist-info/RECORD
