Metadata-Version: 2.1
Name: flex-lumped
Version: 1.0.0
Summary: Dev version for a FLEX-lumped hydrological model using BMI for eWaterCycle.
Author-email: David Haasnoot <davidhaasnoot@gmail.com>
License-Expression: Apache-2.0
License-File: LICENSE.txt
Requires-Dist: bmipy
Requires-Dist: netcdf4
Requires-Dist: numpy
Requires-Dist: pandas
Requires-Dist: xarray
